httpx_ip_rotator/__init__.py
httpx_ip_rotator/async_ip_rotator.py
httpx_ip_rotator/ip_rotator.py
httpx_ip_rotator/rotator.py
httpx_ip_rotator-0.1.4.dist-info/METADATA
httpx_ip_rotator-0.1.4.dist-info/WHEEL
httpx_ip_rotator-0.1.4.dist-info/licenses/LICENSE
httpx_ip_rotator-0.1.4.dist-info/RECORD
