Metadata-Version: 2.3
Name: httpx-ip-rotator
Version: 0.1.4
Summary: Rotate through IPs in Python with HTTPX using AWS API Gateway.
Project-URL: Homepage, https://github.com/alexbruf/httpx-ip-rotator
Project-URL: Issues, https://github.com/alexbruf/httpx-ip-rotator/issues
Author-email: Alex Brufsky <alex@brufsky.org>
License:                     GNU GENERAL PUBLIC LICENSE
License-File: LICENSE
Classifier: License :: OSI Approved :: MIT License
Classifier: Operating System :: OS Independent
Classifier: Programming Language :: Python :: 3
Requires-Python: >=3.8
Requires-Dist: boto3>=1.35.20
Requires-Dist: botocore>=1.35.20
Requires-Dist: httpx>=0.27.2
